README.md
setup.py
library/__init__.py
library/blendlib.c
library/blendlib.so
library/library.py
library/main.py
library/wsl.py
photoblend2.egg-info/PKG-INFO
photoblend2.egg-info/SOURCES.txt
photoblend2.egg-info/dependency_links.txt
photoblend2.egg-info/entry_points.txt
photoblend2.egg-info/requires.txt
photoblend2.egg-info/top_level.txt