Metadata-Version: 1.0
Name: photoblend2
Version: 0.0.1
Summary: Photoblend is a custom PyQt5 & C++ image editor app with blending mode features, filters and othermanipulation options to render unique and creative images.
Home-page: https://github.com/aausek/PhotoBlend
Author: Team Senioritis
Author-email: UNKNOWN
License: MIT
Platform: UNKNOWN
